dspace_rest_client/__init__.py
dspace_rest_client/client.py
dspace_rest_client/models.py
dspace_rest_client-0.1.13.dist-info/LICENSE.txt
dspace_rest_client-0.1.13.dist-info/METADATA
dspace_rest_client-0.1.13.dist-info/WHEEL
dspace_rest_client-0.1.13.dist-info/top_level.txt
dspace_rest_client-0.1.13.dist-info/RECORD
