Metadata-Version: 2.1
Name: dspace-rest-client
Version: 0.1.13
Summary: A DSpace 7 REST API client library
Home-page: https://github.com/the-library-code/dspace-rest-client
Author: Kim Shepherd
Author-email: kim@the-library-code.de
License: BSD-3-Clause
Project-URL: Documentation, https://github.com/the-library-code/dspace-rest-python/blob/main/README.md
Project-URL: GitHub, https://github.com/the-library-code/dspace-rest-python
Project-URL: Changelog, https://github.com/the-library-code/dspace-rest-python/blob/main/CHANGELOG.md
Platform: UNKNOWN
Classifier: Programming Language :: Python :: 3.8
Classifier: Programming Language :: Python :: 3.9
Classifier: Programming Language :: Python :: 3.10
Classifier: Programming Language :: Python :: 3.11
Classifier: Programming Language :: Python :: 3.12
Classifier: License :: OSI Approved :: BSD License
Classifier: Operating System :: OS Independent
Requires-Python: >=3.8.0
License-File: LICENSE.txt
Requires-Dist: pysolr (>=3.10.0)
Requires-Dist: requests (>=2.32.3)
